cmburn/__init__.py
cmburn/__version__.py
cmburn/general/__init__.py
cmburn/general/cmburn.py
cmburn/pi/__init__.py
cmburn/pi/burner.py
cmburn/pi/cmpiburn.py
cmburn/pi/hardware.py
cmburn/pi/image.py
cmburn/pi/util.py
cm_burn-0.3.2.dist-info/LICENSE
cm_burn-0.3.2.dist-info/METADATA
cm_burn-0.3.2.dist-info/WHEEL
cm_burn-0.3.2.dist-info/entry_points.txt
cm_burn-0.3.2.dist-info/top_level.txt
cm_burn-0.3.2.dist-info/RECORD
