Metadata-Version: 2.1
Name: cm-burn
Version: 0.3.2
Summary: A command to burn many SD cards for building PI clusters
Home-page: https://github.com/cloudmesh/cm-burn.py
Author: Cloudmesh Team
Author-email: laszewski@gmail.comm
License: UNKNOWN
Project-URL: Bug Reports, https://github.com/cloudmesh/cm-burn.py/issues
Project-URL: Source, https://github.com/cloudmesh/cm-burn.py/
Keywords: Raspberry PI SDcard cloudmesh
Platform: UNKNOWN
Classifier: Development Status :: 3 - Alpha
Classifier: Topic :: Software Development :: Build Tools
Classifier: License :: OSI Approved :: Apache Software License
Classifier: Programming Language :: Python :: 3.7
Classifier: Programming Language :: Python :: 3.8
Classifier: Environment :: Console
Classifier: Intended Audience :: Developers
Classifier: Intended Audience :: System Administrators
Classifier: Intended Audience :: Information Technology
Classifier: Intended Audience :: Education
Classifier: Intended Audience :: Science/Research
Classifier: Topic :: System
Classifier: Topic :: System :: Distributed Computing
Classifier: Topic :: System :: Shells
Classifier: Topic :: Utilities
Requires-Dist: python-hostlist
Requires-Dist: docopt
Requires-Dist: prompter
Requires-Dist: requests
Requires-Dist: pyyaml
Requires-Dist: oyaml
Requires-Dist: cloudmesh-common
Provides-Extra: dev
Requires-Dist: check-manifest ; extra == 'dev'
Provides-Extra: test
Requires-Dist: coverage ; extra == 'test'
